bbgws/__init__.py
bbgws/event.py
bbgws/steps/__init__.py
bbgws/steps/_stagefilter.py
bbgws/steps/artifacts.py
bbgws/steps/asyncbuild.py
bbgws/steps/gws.py
bbgws/webhook/__init__.py
bbgws/webhook/gws.py
bbgws-0.1.1.dist-info/LICENSE
bbgws-0.1.1.dist-info/LICENSE-GPL-3.0
bbgws-0.1.1.dist-info/METADATA
bbgws-0.1.1.dist-info/WHEEL
bbgws-0.1.1.dist-info/entry_points.txt
bbgws-0.1.1.dist-info/RECORD
