Metadata-Version: 2.1
Name: bbgws
Version: 0.1.1
Summary: Plugins for actionbot (a buildbot-based preconfigured CI)
License: LGPL-3.0-only
Author: Michal Goral
Author-email: dev@goral.net.pl
Requires-Python: >=3.11,<4.0
Classifier: Development Status :: 4 - Beta
Classifier: Environment :: Plugins
Classifier: Intended Audience :: Developers
Classifier: License :: OSI Approved :: GNU Lesser General Public License v3 (LGPLv3)
Classifier: Programming Language :: Python :: 3
Classifier: Programming Language :: Python :: 3.11
Classifier: Programming Language :: Python :: 3.12
